cryption/__init__.py
cryption-0.4.0.dist-info/LICENSE
cryption-0.4.0.dist-info/METADATA
cryption-0.4.0.dist-info/WHEEL
cryption-0.4.0.dist-info/top_level.txt
cryption-0.4.0.dist-info/RECORD
